[
  {
    "ContainingType": "TrinxZap.API.Controllers.PedidoController",
    "Method": "GetAll",
    "RelativePath": "api/Pedido",
    "HttpMethod": "GET",
    "IsController": true,
    "Order": 0,
    "Parameters": [],
    "ReturnTypes": []
  },
  {
    "ContainingType": "TrinxZap.API.Controllers.PedidoController",
    "Method": "Create",
    "RelativePath": "api/Pedido",
    "HttpMethod": "POST",
    "IsController": true,
    "Order": 0,
    "Parameters": [
      {
        "Name": "pedido",
        "Type": "Pedido",
        "IsRequired": true
      }
    ],
    "ReturnTypes": []
  },
  {
    "ContainingType": "TrinxZap.API.Controllers.PedidoController",
    "Method": "GetById",
    "RelativePath": "api/Pedido/{id}",
    "HttpMethod": "GET",
    "IsController": true,
    "Order": 0,
    "Parameters": [
      {
        "Name": "id",
        "Type": "System.Int32",
        "IsRequired": true
      }
    ],
    "ReturnTypes": []
  },
  {
    "ContainingType": "TrinxZap.API.Controllers.PedidoController",
    "Method": "Update",
    "RelativePath": "api/Pedido/{id}",
    "HttpMethod": "PUT",
    "IsController": true,
    "Order": 0,
    "Parameters": [
      {
        "Name": "id",
        "Type": "System.Int32",
        "IsRequired": true
      },
      {
        "Name": "pedido",
        "Type": "Pedido",
        "IsRequired": true
      }
    ],
    "ReturnTypes": []
  },
  {
    "ContainingType": "TrinxZap.API.Controllers.PedidoController",
    "Method": "Delete",
    "RelativePath": "api/Pedido/{id}",
    "HttpMethod": "DELETE",
    "IsController": true,
    "Order": 0,
    "Parameters": [
      {
        "Name": "id",
        "Type": "System.Int32",
        "IsRequired": true
      }
    ],
    "ReturnTypes": []
  }
]